{
    "collection_name": "water-sprinkler-3x3",
    "animated": true,
    "meshes": {
        "static": {
            "file": "models/water-sprinkler-3x3_static.obj",
            "offset_from_origin": [
                0.0,
                0.0,
                0.0
            ],
            "texture_material": false,
            "texture_path": null
        },
        "animated": {
            "file": "models/water-sprinkler-3x3_animated.obj",
            "offset_from_origin": [
                -1.9660918712615967,
                0.8674116730690002,
                -1.3803045749664307
            ],
            "texture_material": false,
            "texture_path": null,
            "animation": {
                "start_position": [
                    0.0,
                    0.0,
                    1.0156269073486328
                ],
                "end_position": [
                    0.0,
                    0.0,
                    1.0156269073486328
                ],
                "start_rotation": [
                    0.0,
                    0.0,
                    0.0,
                    1.0
                ],
                "end_rotation": [
                    0.0,
                    0.0,
                    0.0,
                    1.0
                ],
                "start_scale": [
                    1.0,
                    1.0,
                    1.0
                ],
                "end_scale": [
                    1.0,
                    1.0,
                    1.0
                ]
            }
        }
    }
}